_examples/__init__.py
examples/README.rst
examples/__init__.py
projectreport/__init__.py
projectreport/config.py
projectreport/logger.py
projectreport/version.py
projectreport/analyzer/__init__.py
projectreport/analyzer/analysis.py
projectreport/analyzer/analyzable.py
projectreport/analyzer/folder.py
projectreport/analyzer/module.py
projectreport/analyzer/project.py
projectreport/analyzer/parsers/__init__.py
projectreport/analyzer/parsers/base.py
projectreport/analyzer/parsers/index.py
projectreport/analyzer/parsers/javascript.py
projectreport/analyzer/parsers/python.py
projectreport/analyzer/ts/__init__.py
projectreport/analyzer/ts/base.py
projectreport/analyzer/ts/github.py
projectreport/analyzer/ts/types.py
projectreport/finder/__init__.py
projectreport/finder/base.py
projectreport/finder/combine.py
projectreport/finder/git.py
projectreport/finder/js.py
projectreport/finder/python.py
projectreport/report/__init__.py
projectreport/report/base.py
projectreport/report/json.py
projectreport/report/latex.py
projectreport/report/project.py
projectreport/report/report.py
projectreport/searcher/__init__.py
projectreport/searcher/rotating_list.py
projectreport/searcher/search.py
projectreport/tools/__init__.py
projectreport/tools/expand_glob.py
projectreport/tools/monkey_patch_github.py
tests/__init__.py
tests/base.py
tests/test_finder.py
tests/test_project.py
tests/test_report.py
tests/test_version.py
tests/input_data/js_example/index.js
tests/input_data/js_example/package.json
tests/input_data/python_example/__init__.py
tests/input_data/reports/report.json
tests/input_data/reports/report.tex
tests/input_data/reports/report.yml
project_report-0.6.0.dist-info/LICENSE.md
project_report-0.6.0.dist-info/METADATA
project_report-0.6.0.dist-info/WHEEL
project_report-0.6.0.dist-info/top_level.txt
project_report-0.6.0.dist-info/RECORD
