Metadata-Version: 2.1
Name: project-report
Version: 0.6.0
Summary: Find software projects, analyze them, and output a report.
Home-page: https://github.com/nickderobertis/project-report/
Author: Nick DeRobertis
Author-email: whoopnip@gmail.com
License: MIT
Project-URL: Code, https://github.com/nickderobertis/project-report/
Project-URL: Documentation, https://nickderobertis.github.io/project-report/
Platform: UNKNOWN
Classifier: Development Status :: 3 - Alpha
Classifier: Intended Audience :: Developers
Classifier: Programming Language :: Python :: 3.6
Classifier: Programming Language :: Python :: 3.7
License-File: LICENSE.md
Requires-Dist: pygount
Requires-Dist: cached-property
Requires-Dist: gitpython
Requires-Dist: pyexlatex
Requires-Dist: PyYAML
Requires-Dist: PyGithub
Requires-Dist: semver
Requires-Dist: getversion
